LICENCE
MANIFEST.in
README.md
setup.py
setuptools_green/__init__.py
setuptools_green.egg-info/PKG-INFO
setuptools_green.egg-info/SOURCES.txt
setuptools_green.egg-info/dependency_links.txt
setuptools_green.egg-info/entry_points.txt
setuptools_green.egg-info/requires.txt
setuptools_green.egg-info/top_level.txt
setuptools_green.egg-info/zip-safe
test/__init__.py
test/test_setuptools_green.py